{
    "Blog": "Blog",
    "BlogId": "Blog ID",
    "BlogImage": "Blog Image",
    "BlogTitle": "Blog Title",
    "BlogContent": "Blog Content",
    "UserId": "User ID",
    "Book": "Book",
    "BookTitle": "Book Title",
    "BookContent": "Book Content",
    "BookPublisher": "Book Publisher",
    "BookAuthor": "Book Author",
    "BookYearPublic": "Book Year of Publication",
    "BookImage": "Book Image",
    "Magazine": "Magazine",
    "MagazineId": "Magazine ID",
    "MagazineTitle": "Magazine Title",
    "MagazineContent": "Magazine Content",
    "MagazineImage": "Magazine Image",
    "Music": "Music",
    "MusicId": "Music ID",
    "MusicTitle": "Music Title",
    "MusicAuthor": "Music Author",
    "MusicImage": "Music Image",
    "MusicAudio": "Music Audio",
    "SlideImage": "Slide Images",
    "SlideImageTitle": "Slide Image Title",
    "SlideImageImage": "Slide Image Content",
    "SlideShowTitle": "Slide Show Title",
    "SlideShowImage": "Slide Poster Image",
    "SolemnVisit": "Leader Visit",
    "SolemnVisitId": "Leader Visit ID",
    "SolemnVisitName": "Leader Name",
    "PortraitImage": "Leader Portrait Image",
    "ImageLink": "Image Link",
    "LetterImage": "Visit Letter Image",
    "Music": "Music",
    "Video": "Video",
    "VideoId": "Video ID",
    "VideoTitle": "Video Title",
    "VideoLink": "Video Link",
    "TopicCapture": "Topic Capture",
    "MediaTypeId": "Media Type",

    "InvalidValue": "{0} is invalid.",
    "NotEmpty": "{0} cannot be empty.",
    "MaxLength": "{0} can have a maximum of {1} characters",
    "LengthBetween": "{0} must be between {1} and {2}",
    "NotFound": "{0} not found.",
    "InvalidFileType": "The format is not accepted, please choose a valid format ({0})",

    "UploadImageCloudinaryFailed": "Failed to upload image to Cloudinary.",
    "UploadAudioCloudinaryFailed": "Failed to upload audio to Cloudinary.",
    "UploadPDFCloudinaryFailed": "Failed to upload PDF to Cloudinary.",
    "AddBlogFailed": "Failed to add blog.",
    "DeleteBlogFailed": "Failed to delete blog.",
    "UpdateBlogFailed": "Failed to update blog.",
    "UpdateBookFailed": "Failed to update book.",
    "AddBookFailed": "Failed to add book.",
    "DeleteBookFailed": "Failed to delete book.",
    "UpdateMagazineFailed": "Failed to update magazine.",
    "AddMagazineFailed": "Failed to add magazine.",
    "DeleteMagazineFailed": "Failed to delete magazine.",
    "AddMusicFailed": "Failed to add music.",
    "UpdateMusicFailed": "Failed to update music.",
    "DeleteMusicFailed": "Failed to delete music."
}
